todopyedu/__init__.py
todopyedu/__main__.py
todopyedu/cli.py
todopyedu/config.py
todopyedu/database.py
todopyedu/dist/todopyedu-0.3.0-py3-none-any.whl
todopyedu/dist/todopyedu-0.3.0.tar.gz
todopyedu/todopyedu.py
todopyedup-0.1.0.dist-info/entry_points.txt
todopyedup-0.1.0.dist-info/WHEEL
todopyedup-0.1.0.dist-info/METADATA
todopyedup-0.1.0.dist-info/RECORD
