Metadata-Version: 2.1
Name: todopyedup
Version: 0.1.0
Summary: Issue log created by educational purposes
Home-page: https://gitlab.com/kekbek/python-todo
Author: kekbek
Author-email: vadyusha.surin@gmail.com
Requires-Python: >=3.6,<4.0
Classifier: Programming Language :: Python :: 3
Classifier: Programming Language :: Python :: 3.10
Classifier: Programming Language :: Python :: 3.6
Classifier: Programming Language :: Python :: 3.7
Classifier: Programming Language :: Python :: 3.8
Classifier: Programming Language :: Python :: 3.9
Requires-Dist: colorama (>=0.4.4,<0.5.0)
Requires-Dist: prettytable (>=2.4.0,<3.0.0)
Requires-Dist: shellingham (>=1.4.0,<2.0.0)
Requires-Dist: typer (>=0.4.0,<0.5.0)
